hgutilities/__init__.py
hgutilities/Documentation/__init__.py
hgutilities/defaults/__init__.py
hgutilities/defaults/docs.py
hgutilities/defaults/inherit.py
hgutilities/defaults/loaddefaults.py
hgutilities/defaults/processkwargs.py
hgutilities/defaults/Documentation/__init__.py
hgutilities/plotting/__init__.py
hgutilities/plotting/animate.py
hgutilities/plotting/figure.py
hgutilities/plotting/figures.py
hgutilities/plotting/plotfunctions.py
hgutilities/plotting/quick.py
hgutilities/plotting/Documentation/__init__.py
hgutilities/plotting/datatypes/__init__.py
hgutilities/plotting/datatypes/bar.py
hgutilities/plotting/datatypes/bars.py
hgutilities/plotting/datatypes/colorplot.py
hgutilities/plotting/datatypes/data.py
hgutilities/plotting/datatypes/line.py
hgutilities/plotting/datatypes/lines.py
hgutilities/plotting/datatypes/pie.py
hgutilities/plotting/datatypes/surface.py
hgutilities/plotting/datatypes/Documentation/__init__.py
hgutilities/plotting/plottypes/__init__.py
hgutilities/plotting/plottypes/plot.py
hgutilities/plotting/plottypes/plotbars.py
hgutilities/plotting/plottypes/plotcolorplot.py
hgutilities/plotting/plottypes/plotlines.py
hgutilities/plotting/plottypes/plotpie.py
hgutilities/plotting/plottypes/plotsurface.py
hgutilities/plotting/plottypes/Documentation/__init__.py
hgutilities/plotting/plotutils/__init__.py
hgutilities/plotting/plotutils/figuresize.py
hgutilities/plotting/plotutils/griddimensions.py
hgutilities/plotting/plotutils/plotshape.py
hgutilities/plotting/plotutils/savefigure.py
hgutilities/utils/__init__.py
hgutilities/utils/filenames.py
hgutilities/utils/groups.py
hgutilities/utils/iterables.py
hgutilities/utils/json.py
hgutilities/utils/paths.py
hgutilities/utils/plots.py
hgutilities/utils/printiterable.py
hgutilities/utils/readwrite.py
hgutilities/utils/Documentation/__init__.py
hgutilities-1.1.5.dist-info/LICENSE.md
hgutilities-1.1.5.dist-info/METADATA
hgutilities-1.1.5.dist-info/WHEEL
hgutilities-1.1.5.dist-info/top_level.txt
hgutilities-1.1.5.dist-info/RECORD
