Metadata-Version: 2.1
Name: hgutilities
Version: 1.1.5
Summary: A triple of tools used for plotting, handling key-words, and utilities
Author-email: Henry Ginn <henryginn137@gmail.com>
Keywords: python,matplotlib,plotting,default,keywords,utils
Classifier: Development Status :: 4 - Beta
Classifier: Intended Audience :: Developers
Classifier: Programming Language :: Python :: 3
Classifier: License :: OSI Approved :: GNU General Public License v3 (GPLv3)
Classifier: Natural Language :: English
Classifier: Operating System :: Unix
Classifier: Operating System :: Microsoft :: Windows
Requires-Python: >=3.8
License-File: LICENSE.md
Requires-Dist: matplotlib
Requires-Dist: numpy
Requires-Dist: screeninfo
Requires-Dist: pillow
